setup.py
pycebox/__init__.py
pycebox/ice.py
pycebox.egg-info/PKG-INFO
pycebox.egg-info/SOURCES.txt
pycebox.egg-info/dependency_links.txt
pycebox.egg-info/requires.txt
pycebox.egg-info/top_level.txt
test/test.py