Metadata-Version: 1.0
Name: pycebox
Version: 0.0.1
Summary: The Python Individual Conditional Expectation Toolbox
Home-page: https://github.com/AustinRochford/PyCEbox
Author: Austin Rochford
Author-email: austin.rochford@gmail.com
License: MIT
Platform: UNKNOWN
